mltools/__init__.py
mltools/data.py
mltools/draw.py
mltools/learn.py
mltools/tokenize.py
mltools/utils.py
wliafe_mltools-1.0.11.dist-info/licenses/LICENSE
wliafe_mltools-1.0.11.dist-info/WHEEL
wliafe_mltools-1.0.11.dist-info/entry_points.txt
wliafe_mltools-1.0.11.dist-info/METADATA
wliafe_mltools-1.0.11.dist-info/RECORD
