Metadata-Version: 2.4
Name: wliafe-mltools
Version: 1.0.11
Summary: A machine learning tools library
Author: wliafe
Author-email: wliafe <914099435@qq.com>
License-Expression: Apache-2.0
License-File: LICENSE
Classifier: License :: OSI Approved :: Apache Software License
Classifier: Programming Language :: Python :: 3
Classifier: Programming Language :: Python :: 3.8
Classifier: Programming Language :: Python :: 3.9
Classifier: Programming Language :: Python :: 3.10
Classifier: Operating System :: OS Independent
Requires-Dist: httpx>=0.28.1
Requires-Dist: jupyter>=1.0.0
Requires-Dist: matplotlib>=3.5.1
Requires-Dist: pandas>=1.2.4
Requires-Dist: tqdm>=4.67.1
Requires-Dist: torch>=2.1.0,<2.5.0 ; python_full_version == '3.8.*'
Requires-Dist: torchvision>=0.16.0,<0.20.0 ; python_full_version == '3.8.*'
Requires-Dist: torchaudio>=2.1.0,<2.5.0 ; python_full_version == '3.8.*'
Requires-Dist: torch>=2.5.0 ; python_full_version >= '3.9'
Requires-Dist: torchvision>=0.20.0 ; python_full_version >= '3.9'
Requires-Dist: torchaudio>=2.5.0 ; python_full_version >= '3.9'
Requires-Python: >=3.8
Project-URL: Documentation, https://wliafe-mltools.readthedocs.io/
Project-URL: Homepage, https://github.com/wliafe/mltools
Project-URL: Issues, https://github.com/wliafe/mltools/issues
Project-URL: Repository, https://github.com/wliafe/mltools.git
